tess_downloader/.DS_Store
tess_downloader/__init__.py
tess_downloader/__main__.py
tess_downloader/api.py
tess_downloader/cli.py
tess_downloader/py.typed
tess_downloader/version.py
tess_downloader-0.0.5.dist-info/licenses/LICENSE
tess_downloader-0.0.5.dist-info/WHEEL
tess_downloader-0.0.5.dist-info/entry_points.txt
tess_downloader-0.0.5.dist-info/METADATA
tess_downloader-0.0.5.dist-info/RECORD
