Metadata-Version: 2.4
Name: tess_downloader
Version: 0.0.5
Summary: Download and structure learning materials from TeSS
Keywords: snekpack,cookiecutter
Author: Charles Tapley Hoyt
Author-email: Charles Tapley Hoyt <cthoyt@gmail.com>
License-File: LICENSE
Classifier: Development Status :: 1 - Planning
Classifier: Environment :: Console
Classifier: Intended Audience :: Developers
Classifier: License :: OSI Approved :: MIT License
Classifier: Operating System :: OS Independent
Classifier: Framework :: Pytest
Classifier: Framework :: tox
Classifier: Framework :: Sphinx
Classifier: Natural Language :: English
Classifier: Programming Language :: Python
Classifier: Programming Language :: Python :: 3.12
Classifier: Programming Language :: Python :: 3.13
Classifier: Programming Language :: Python :: 3 :: Only
Classifier: Typing :: Typed
Requires-Dist: tqdm
Requires-Dist: click
Requires-Dist: more-click
Requires-Dist: typing-extensions
Requires-Dist: requests
Requires-Dist: pydantic
Requires-Dist: pystow
Maintainer: Charles Tapley Hoyt
Maintainer-email: Charles Tapley Hoyt <cthoyt@gmail.com>
Requires-Python: >=3.12
Project-URL: Bug Tracker, https://github.com/cthoyt/tess-downloader/issues
Project-URL: Documentation, https://tess_downloader.readthedocs.io
Project-URL: Funding, https://github.com/sponsors/cthoyt
Project-URL: Homepage, https://github.com/cthoyt/tess-downloader
Project-URL: Repository, https://github.com/cthoyt/tess-downloader.git
